LICENSE
MANIFEST.in
README.md
requirements.txt
setup.py
src/pii_preprocess/__init__.py
src/pii_preprocess/defs.py
src/pii_preprocess.egg-info/PKG-INFO
src/pii_preprocess.egg-info/SOURCES.txt
src/pii_preprocess.egg-info/dependency_links.txt
src/pii_preprocess.egg-info/entry_points.txt
src/pii_preprocess.egg-info/requires.txt
src/pii_preprocess.egg-info/top_level.txt
src/pii_preprocess/app/__init__.py
src/pii_preprocess/app/csvdoc.py
src/pii_preprocess/app/doc.py
src/pii_preprocess/app/textdoc.py
src/pii_preprocess/doc/__init__.py
src/pii_preprocess/doc/csv.py
src/pii_preprocess/doc/utils.py
src/pii_preprocess/doc/msoffice/__init__.py
src/pii_preprocess/doc/msoffice/msword.py
src/pii_preprocess/doc/text/__init__.py
src/pii_preprocess/doc/text/defs.py
src/pii_preprocess/doc/text/load.py
src/pii_preprocess/doc/text/read/__init__.py
src/pii_preprocess/doc/text/read/base.py
src/pii_preprocess/doc/text/read/read_lines.py
src/pii_preprocess/doc/text/read/read_para.py
src/pii_preprocess/doc/text/read/read_single.py
src/pii_preprocess/doc/text/read/read_tree.py
src/pii_preprocess/doc/text/read/read_words.py
src/pii_preprocess/loader/__init__.py
src/pii_preprocess/loader/loader.py
src/pii_preprocess/resources/__init__.py
src/pii_preprocess/resources/doc-loader.json