Metadata-Version: 2.1
Name: pii-preprocess
Version: 0.1.0
Summary: Document preprocessing for PII Management
Home-page: https://github.com/piisa/pii-preprocess
Download-URL: https://github.com/piisa/pii-preprocess/tarball/v0.1.0
Author: Paulo Villegas
Author-email: paulo.vllgs@gmail.com
License: Apache
Keywords: PIISA, PII
Classifier: Programming Language :: Python :: 3 :: Only
Classifier: License :: OSI Approved :: Apache Software License
Classifier: Development Status :: 4 - Beta
Classifier: Topic :: Software Development :: Libraries :: Application Frameworks
Requires-Python: >=3.8
Provides-Extra: test
License-File: LICENSE
